{"commitInfo":{"timestamp":1779387631224,"operation":"WRITE","operationParameters":{"mode":"Overwrite"},"engineInfo":"delta-rs:py-1.6.0","clientVersion":"delta-rs.py-1.6.0","operationMetrics":{"execution_time_ms":1,"num_added_files":1,"num_added_rows":12,"num_partitions":0,"num_removed_files":1}}}
{"remove":{"path":"part-00000-1ab9c6fc-1b5c-4542-9b80-9e0cfb9e3e0a-c000.snappy.parquet","dataChange":true,"deletionTimestamp":1779387631223,"extendedFileMetadata":true,"partitionValues":{},"size":2909}}
{"add":{"path":"part-00000-573d0334-2a5d-4155-ae50-3785b302d16a-c000.snappy.parquet","partitionValues":{},"size":2980,"modificationTime":1779387631224,"dataChange":true,"stats":"{\"numRecords\":12,\"minValues\":{\"loyalty_tier\":\"bronze\",\"amount\":117.58,\"timestamp\":\"2026-03-16T10:00:00\",\"discount_code\":\"FREESHIP\",\"product_id\":2001,\"transaction_id\":356000,\"region\":\"EAST\",\"customer_id\":501},\"maxValues\":{\"customer_id\":506,\"amount\":571.14,\"region\":\"WEST\",\"discount_code\":\"SAVE5\",\"transaction_id\":356011,\"loyalty_tier\":\"silver\",\"product_id\":2004,\"timestamp\":\"2026-03-16T10:00:00\"},\"nullCount\":{\"transaction_id\":0,\"amount\":0,\"timestamp\":0,\"customer_id\":0,\"discount_code\":2,\"region\":0,\"loyalty_tier\":0,\"product_id\":0}}","tags":null,"baseRowId":null,"defaultRowCommitVersion":null,"clusteringProvider":null}}