{"commitInfo":{"timestamp":1779387822299,"operation":"WRITE","operationParameters":{"mode":"Append"},"engineInfo":"delta-rs:py-1.6.0","operationMetrics":{"execution_time_ms":0,"num_added_files":1,"num_added_rows":1,"num_partitions":0,"num_removed_files":0},"clientVersion":"delta-rs.py-1.6.0"}}
{"metaData":{"id":"6ed907cf-e00b-4efc-bf42-d61eeb6ccab4","name":null,"description":null,"format":{"provider":"parquet","options":{}},"schemaString":"{\"type\":\"struct\",\"fields\":[{\"name\":\"id\",\"type\":\"long\",\"nullable\":true,\"metadata\":{}},{\"name\":\"a\",\"type\":\"string\",\"nullable\":true,\"metadata\":{}},{\"name\":\"b\",\"type\":\"string\",\"nullable\":true,\"metadata\":{}},{\"name\":\"c\",\"type\":\"string\",\"nullable\":true,\"metadata\":{}}]}","partitionColumns":[],"createdTime":1779387822294,"configuration":{}}}
{"add":{"path":"part-00000-8d0c123d-85eb-40e2-95d2-8be37a0c3711-c000.snappy.parquet","partitionValues":{},"size":1190,"modificationTime":1779387822299,"dataChange":true,"stats":"{\"numRecords\":1,\"minValues\":{\"c\":\"v3\",\"b\":\"v2\",\"a\":\"x\",\"id\":1},\"maxValues\":{\"c\":\"v3\",\"id\":1,\"b\":\"v2\",\"a\":\"x\"},\"nullCount\":{\"c\":0,\"a\":0,\"id\":0,\"b\":0}}","tags":null,"baseRowId":null,"defaultRowCommitVersion":null,"clusteringProvider":null}}